cadnano/__init__.py
cadnano/addinstancecmd.py
cadnano/assembly.py
cadnano/cadnanoqt.py
cadnano/color.py
cadnano/docmodscmd.py
cadnano/document.py
cadnano/objectinstance.py
cadnano/removeinstancecmd.py
cadnano/setpropertycmd.py
cadnano/undocommand.py
cadnano/undostack.py
cadnano/util.py
cadnano/bin/__init__.py
cadnano/bin/appify.py
cadnano/bin/createstl.py
cadnano/bin/main.py
cadnano/controllers/__init__.py
cadnano/controllers/documentcontroller.py
cadnano/controllers/nucleicacidpartitemcontroller.py
cadnano/controllers/oligoitemcontroller.py
cadnano/controllers/partitemcontroller.py
cadnano/controllers/stranditemcontroller.py
cadnano/controllers/viewrootcontroller.py
cadnano/controllers/virtualhelixitemcontroller.py
cadnano/controllers/itemcontrollers/__init__.py
cadnano/controllers/itemcontrollers/nucleicacidpartitemcontroller.py
cadnano/controllers/itemcontrollers/oligoitemcontroller.py
cadnano/controllers/itemcontrollers/partitemcontroller.py
cadnano/controllers/itemcontrollers/virtualhelixitemcontroller.py
cadnano/controllers/itemcontrollers/strand/__init__.py
cadnano/controllers/itemcontrollers/strand/abstractstranditemcontroller.py
cadnano/controllers/itemcontrollers/strand/endpointitemcontroller.py
cadnano/controllers/itemcontrollers/strand/stranditemcontroller.py
cadnano/decorators/__init__.py
cadnano/decorators/insertion.py
cadnano/extras/__init__.py
cadnano/extras/dnasequences.py
cadnano/extras/sequencemods.py
cadnano/extras/wrapapi.py
cadnano/extras/install_exe/__init__.py
cadnano/extras/install_exe/cadnano-script.py
cadnano/extras/install_exe/cadnanoinstall.py
cadnano/extras/math/__init__.py
cadnano/extras/math/box.py
cadnano/extras/math/face.py
cadnano/extras/math/matrix3.py
cadnano/extras/math/matrix4.py
cadnano/extras/math/solid.py
cadnano/extras/math/vector.py
cadnano/fileio/__init__.py
cadnano/fileio/c25decode.py
cadnano/fileio/decode.py
cadnano/fileio/encode.py
cadnano/fileio/lattice.py
cadnano-2.5.2.1.dist-info/DESCRIPTION.rst
cadnano-2.5.2.1.dist-info/METADATA
cadnano-2.5.2.1.dist-info/RECORD
cadnano-2.5.2.1.dist-info/WHEEL
cadnano-2.5.2.1.dist-info/entry_points.txt
cadnano-2.5.2.1.dist-info/metadata.json
cadnano-2.5.2.1.dist-info/top_level.txt
