Metadata-Version: 2.0
Name: cadnano
Version: 2.5.2.1
Summary: computer-aided design tool for creating DNA nanostructures
Home-page: https://github.com/cadnano/cadnano2.5
Author: Nick Conway, Shawn Douglas
Author-email: a.grinner@gmail.com
License: multiple
Platform: any
Classifier: Programming Language :: C
Classifier: Programming Language :: Python
Classifier: Programming Language :: Python :: 3.5
Classifier: Programming Language :: Python :: 3.6
Classifier: Development Status :: 4 - Beta
Classifier: Intended Audience :: Science/Research
Classifier: Topic :: Scientific/Engineering :: Bio-Informatics
Classifier: License :: OSI Approved :: GNU General Public License v3 (GPLv3)
Classifier: License :: OSI Approved :: BSD License
Requires-Dist: sip (>=4.19.7)
Requires-Dist: PyQt5 (>=5.10.0)
Requires-Dist: numpy (>=1.10.0)
Requires-Dist: pandas (>=0.18)
Requires-Dist: pytz (>=2011k)
Requires-Dist: python-dateutil (>=2)
Requires-Dist: termcolor (>=1.1.0)
